MANIFEST.in
setup.py
./__init__.py
./__openerp__.py
data/account_chart.xml
data/account_tax.xml
data/account_tax_code.xml
data/account_user_types.xml
data/l10n_chart_ve_wizard.xml
i18n/ar.po
i18n/ca.po
i18n/da.po
i18n/de.po
i18n/es.po
i18n/es_CR.po
i18n/es_MX.po
i18n/es_PY.po
i18n/es_VE.po
i18n/gl.po
i18n/it.po
i18n/l10n_ve.pot
i18n/nl.po
i18n/pt.po
i18n/pt_BR.po
i18n/ro.po
i18n/sl.po
i18n/sr@latin.po
i18n/tr.po
images/config_chart_l10n_ve.jpeg
images/l10n_ve_chart.jpeg
openerp_l10n_ve.egg-info/PKG-INFO
openerp_l10n_ve.egg-info/SOURCES.txt
openerp_l10n_ve.egg-info/dependency_links.txt
openerp_l10n_ve.egg-info/requires.txt
openerp_l10n_ve.egg-info/top_level.txt
static/src/img/icon.png